hat/HAT_main.py
hat/Phasing.py
hat/PloidyBlocks.py
hat/ReadInput.py
hat/Seeds.py
hat/Visualization.py
hat/__init__.py
HAT_phasing-0.1.8.dist-info/LICENSE
HAT_phasing-0.1.8.dist-info/METADATA
HAT_phasing-0.1.8.dist-info/WHEEL
HAT_phasing-0.1.8.dist-info/entry_points.txt
HAT_phasing-0.1.8.dist-info/top_level.txt
HAT_phasing-0.1.8.dist-info/RECORD
