Metadata-Version: 2.1
Name: HAT-phasing
Version: 0.1.8
Summary: HAT:‌  Haplotype assembly tool that use both long and short reads to reconstruct haplotypes
Home-page: https://github.com/AbeelLab/hat
Author: Ramin Shirali Hossein Zade
Author-email: r.shirali.hz@gmail.com
License: GPL-3.0
Requires-Python: >=3.8
License-File: LICENSE
Requires-Dist: pysam (>=0.19.0)
Requires-Dist: numpy (>=1.22.3)
Requires-Dist: seaborn
Requires-Dist: matplotlib
Requires-Dist: biopython
